{
  "_class": "group",
  "do_objectID": "27B3A825-E406-4548-867F-705944200FE6",
  "exportOptions": {
    "_class": "exportOptions",
    "exportFormats": [
    ],
    "includedLayerIds": [
    ],
    "layerOptions": 0,
    "shouldTrim": false
  },
  "frame": {
    "_class": "rect",
    "constrainProportions": false,
    "height": 89,
    "width": 150,
    "x": 1357,
    "y": 858
  },
  "hasClickThrough": false,
  "isFlippedHorizontal": false,
  "isFlippedVertical": false,
  "isLocked": false,
  "isVisible": true,
  "layerListExpandedType": 2,
  "layers": [
    {
      "class": "shapeGroup",
      "id": "B783ADD0-EE3A-4B4F-BD78-921C2912FAB8"
    },
    {
      "class": "shapeGroup",
      "id": "29820C7F-C031-443D-A9F1-54694264220B"
    },
    {
      "class": "text",
      "id": "029C44B7-32E6-4201-8BB2-EC9A3E74165C"
    },
    {
      "class": "shapeGroup",
      "id": "5F85E8B7-BA02-4570-A848-BC16294773D4"
    },
    {
      "class": "text",
      "id": "D3247CF0-A007-42E5-B979-7D72A0AC43E6"
    }
  ],
  "name": "Dropdown website Copy 4",
  "nameIsFixed": true,
  "resizingConstraint": 63,
  "resizingType": 0,
  "rotation": 0,
  "shouldBreakMaskChain": false,
  "style": {
    "_class": "style",
    "borders": [
      {
        "_class": "border",
        "color": {
          "_class": "color",
          "alpha": 1,
          "blue": 0.2457482993197279,
          "green": 0.1901162006258732,
          "red": 0.1623001512789459
        },
        "fillType": 0,
        "isEnabled": true,
        "position": 0,
        "thickness": 1
      }
    ],
    "endDecorationType": 0,
    "fills": [
      {
        "_class": "fill",
        "color": {
          "_class": "color",
          "alpha": 1,
          "blue": 0.9764705882352941,
          "green": 0.9764705882352941,
          "red": 0.9764705882352941
        },
        "fillType": 0,
        "isEnabled": true,
        "noiseIndex": 0,
        "noiseIntensity": 0,
        "patternFillType": 1,
        "patternTileScale": 1
      }
    ],
    "miterLimit": 10,
    "shadows": [
      {
        "_class": "shadow",
        "blurRadius": 4,
        "color": {
          "_class": "color",
          "alpha": 0.5,
          "blue": 0,
          "green": 0,
          "red": 0
        },
        "contextSettings": {
          "_class": "graphicsContextSettings",
          "blendMode": 0,
          "opacity": 1
        },
        "isEnabled": false,
        "offsetX": 0,
        "offsetY": 2,
        "spread": 0
      }
    ],
    "startDecorationType": 0
  }
}